aman/__init__.py
aman/__main__.py
aman/aman.py
aman/autodoc.py
aman/book.py
aman/config.py
aman/format.py
aman/index.py
aman/parse.py
aman/query.py
aman/scan.py
amiman-0.1.1.dist-info/LICENSE
amiman-0.1.1.dist-info/METADATA
amiman-0.1.1.dist-info/WHEEL
amiman-0.1.1.dist-info/entry_points.txt
amiman-0.1.1.dist-info/top_level.txt
amiman-0.1.1.dist-info/zip-safe
amiman-0.1.1.dist-info/RECORD
