Metadata-Version: 2.1
Name: amiman
Version: 0.1.1
Summary: Browse Amiga autodoc pages like man pages on your modern system
Author-email: Christian Vogelgsang <chris@vogelgsang.org>
License: MIT
Keywords: AmigaOS,autodoc,man page
Classifier: Development Status :: 4 - Beta
Classifier: Intended Audience :: Developers
Classifier: Programming Language :: Python
Classifier: Topic :: System :: Emulators
Requires-Python: >=3.7
License-File: LICENSE
Requires-Dist: termcolor
